executorch/version.py
executorch/backends/apple/coreml/executorchcoreml.pyi
executorch/backends/apple/coreml/compiler/__init__.py
executorch/backends/apple/coreml/compiler/coreml_preprocess.py
executorch/backends/apple/coreml/partition/__init__.py
executorch/backends/apple/coreml/partition/coreml_partitioner.py
executorch/backends/apple/coreml/quantizer/__init__.py
executorch/backends/apple/coreml/quantizer/coreml_quantizer.py
executorch/backends/apple/coreml/runtime/inmemoryfs/setup.py
executorch/backends/apple/coreml/runtime/test/export_stateful_model.py
executorch/backends/apple/coreml/test/test_coreml_partitioner.py
executorch/backends/apple/coreml/test/test_coreml_quantizer.py
executorch/backends/apple/mps/__init__.py
executorch/backends/apple/mps/mps_preprocess.py
executorch/backends/apple/mps/operators/__init__.py
executorch/backends/apple/mps/operators/activation_ops.py
executorch/backends/apple/mps/operators/binary_ops.py
executorch/backends/apple/mps/operators/clamp_ops.py
executorch/backends/apple/mps/operators/constant_ops.py
executorch/backends/apple/mps/operators/convolution_ops.py
executorch/backends/apple/mps/operators/indexing_ops.py
executorch/backends/apple/mps/operators/linear_algebra_ops.py
executorch/backends/apple/mps/operators/node_visitor.py
executorch/backends/apple/mps/operators/normalization_ops.py
executorch/backends/apple/mps/operators/op_clone.py
executorch/backends/apple/mps/operators/op_getitem.py
executorch/backends/apple/mps/operators/op_quant_dequant.py
executorch/backends/apple/mps/operators/op_skip_ops.py
executorch/backends/apple/mps/operators/pad_ops.py
executorch/backends/apple/mps/operators/pooling_ops.py
executorch/backends/apple/mps/operators/range_ops.py
executorch/backends/apple/mps/operators/reduce_ops.py
executorch/backends/apple/mps/operators/shape_ops.py
executorch/backends/apple/mps/operators/unary_ops.py
executorch/backends/apple/mps/partition/__init__.py
executorch/backends/apple/mps/partition/mps_partitioner.py
executorch-0.5.0.dist-info/LICENSE
executorch-0.5.0.dist-info/METADATA
executorch-0.5.0.dist-info/WHEEL
executorch-0.5.0.dist-info/entry_points.txt
executorch-0.5.0.dist-info/top_level.txt
executorch-0.5.0.dist-info/RECORD
