Metadata-Version: 2.2
Name: executorch
Version: 0.5.0
Summary: On-device AI across mobile, embedded and edge for PyTorch
Author-email: PyTorch Team <packages@pytorch.org>
License: BSD License
Project-URL: Homepage, https://pytorch.org/executorch/
Project-URL: Repository, https://github.com/pytorch/executorch
Project-URL: Issues, https://github.com/pytorch/executorch/issues
Project-URL: Changelog, https://github.com/pytorch/executorch/releases
Keywords: pytorch,machine learning
Classifier: Development Status :: 4 - Beta
Classifier: Intended Audience :: Developers
Classifier: Intended Audience :: Education
Classifier: Intended Audience :: Science/Research
Classifier: License :: OSI Approved :: BSD License
Classifier: Topic :: Scientific/Engineering
Classifier: Topic :: Scientific/Engineering :: Mathematics
Classifier: Topic :: Scientific/Engineering :: Artificial Intelligence
Classifier: Topic :: Software Development
Classifier: Topic :: Software Development :: Libraries
Classifier: Topic :: Software Development :: Libraries :: Python Modules
Classifier: Programming Language :: C++
Classifier: Programming Language :: Python :: 3
Classifier: Programming Language :: Python :: 3.10
Classifier: Programming Language :: Python :: 3.11
Classifier: Programming Language :: Python :: 3.12
Requires-Python: >=3.10
License-File: LICENSE
Requires-Dist: expecttest
Requires-Dist: flatbuffers
Requires-Dist: hypothesis
Requires-Dist: mpmath==1.3.0
Requires-Dist: numpy==2.0.0; python_version >= "3.10"
Requires-Dist: packaging
Requires-Dist: pandas==2.2.2; python_version >= "3.10"
Requires-Dist: parameterized
Requires-Dist: pytest
Requires-Dist: pytest-xdist
Requires-Dist: pyyaml
Requires-Dist: ruamel.yaml
Requires-Dist: sympy
Requires-Dist: tabulate
Requires-Dist: torch==2.6.0
Requires-Dist: torchaudio==2.6.0
Requires-Dist: torchvision==0.21.0
Requires-Dist: typing-extensions
